proto2pb2/__init__.py
proto2pb2/command.py
proto2pb2/converter.py
proto2pb2-0.0.1.dist-info/LICENSE
proto2pb2-0.0.1.dist-info/METADATA
proto2pb2-0.0.1.dist-info/WHEEL
proto2pb2-0.0.1.dist-info/dependency_links.txt
proto2pb2-0.0.1.dist-info/entry_points.txt
proto2pb2-0.0.1.dist-info/top_level.txt
proto2pb2-0.0.1.dist-info/RECORD
